snowflake/cli/__about__.py
snowflake/cli/__init__.py
snowflake/cli/_app/__init__.py
snowflake/cli/_app/__main__.py
snowflake/cli/_app/cli_app.py
snowflake/cli/_app/constants.py
snowflake/cli/_app/loggers.py
snowflake/cli/_app/main_typer.py
snowflake/cli/_app/printing.py
snowflake/cli/_app/snow_connector.py
snowflake/cli/_app/telemetry.py
snowflake/cli/_app/version_check.py
snowflake/cli/_app/auth/__init__.py
snowflake/cli/_app/auth/errors.py
snowflake/cli/_app/auth/oidc_providers.py
snowflake/cli/_app/commands_registration/__init__.py
snowflake/cli/_app/commands_registration/builtin_plugins.py
snowflake/cli/_app/commands_registration/command_plugins_loader.py
snowflake/cli/_app/commands_registration/commands_registration_with_callbacks.py
snowflake/cli/_app/commands_registration/exception_logging.py
snowflake/cli/_app/commands_registration/threadsafe.py
snowflake/cli/_app/commands_registration/typer_registration.py
snowflake/cli/_app/dev/__init__.py
snowflake/cli/_app/dev/commands_structure.py
snowflake/cli/_app/dev/pycharm_remote_debug.py
snowflake/cli/_app/dev/docs/__init__.py
snowflake/cli/_app/dev/docs/commands_docs_generator.py
snowflake/cli/_app/dev/docs/generator.py
snowflake/cli/_app/dev/docs/project_definition_docs_generator.py
snowflake/cli/_app/dev/docs/project_definition_generate_json_schema.py
snowflake/cli/_app/dev/docs/template_utils.py
snowflake/cli/_app/dev/docs/templates/definition_description.rst.jinja2
snowflake/cli/_app/dev/docs/templates/overview.rst.jinja2
snowflake/cli/_app/dev/docs/templates/usage.rst.jinja2
snowflake/cli/_plugins/__init__.py
snowflake/cli/_plugins/auth/__init__.py
snowflake/cli/_plugins/auth/plugin_spec.py
snowflake/cli/_plugins/auth/oidc/__init__.py
snowflake/cli/_plugins/auth/oidc/commands.py
snowflake/cli/_plugins/auth/oidc/manager.py
snowflake/cli/_plugins/auth/oidc/plugin_spec.py
snowflake/cli/_plugins/connection/__init__.py
snowflake/cli/_plugins/connection/commands.py
snowflake/cli/_plugins/connection/plugin_spec.py
snowflake_cli-3.13.0.dist-info/METADATA
snowflake_cli-3.13.0.dist-info/WHEEL
snowflake_cli-3.13.0.dist-info/entry_points.txt
snowflake_cli-3.13.0.dist-info/licenses/LICENSE
snowflake_cli-3.13.0.dist-info/RECORD
