Metadata-Version: 2.4
Name: snowflake-cli
Version: 3.13.0
Summary: Snowflake CLI
Project-URL: Source code, https://github.com/snowflakedb/snowflake-cli
Project-URL: Bug Tracker, https://github.com/snowflakedb/snowflake-cli/issues
Author: Snowflake Inc.
License:                                  Apache License
License-File: LICENSE
Classifier: Development Status :: 5 - Production/Stable
Classifier: Environment :: Console
Classifier: Intended Audience :: Developers
Classifier: Intended Audience :: Information Technology
Classifier: Intended Audience :: System Administrators
Classifier: License :: OSI Approved :: Apache Software License
Classifier: Programming Language :: Python :: 3 :: Only
Classifier: Programming Language :: SQL
Classifier: Topic :: Database
Requires-Python: >=3.10
Requires-Dist: click==8.1.8
Requires-Dist: gitpython==3.1.44
Requires-Dist: id==1.5.0
Requires-Dist: jinja2==3.1.6
Requires-Dist: packaging==25.0
Requires-Dist: pip==25.2
Requires-Dist: pluggy==1.6.0
Requires-Dist: prompt-toolkit==3.0.51
Requires-Dist: pydantic==2.11.7
Requires-Dist: pyyaml==6.0.2
Requires-Dist: requests==2.32.4
Requires-Dist: requirements-parser==0.13.0
Requires-Dist: rich==14.0.0
Requires-Dist: setuptools==80.8.0
Requires-Dist: snowflake-connector-python[secure-local-storage]==3.18.0
Requires-Dist: snowflake-core==1.7.0
Requires-Dist: snowflake-snowpark-python==1.33.0; python_version < '3.12'
Requires-Dist: tomlkit==0.13.3
Requires-Dist: typer==0.17.3
Requires-Dist: urllib3<2.6,>=1.24.3
Provides-Extra: development
Requires-Dist: coverage==7.10.4; extra == 'development'
Requires-Dist: factory-boy==3.3.3; extra == 'development'
Requires-Dist: faker==37.4.0; extra == 'development'
Requires-Dist: pre-commit>=3.5.0; extra == 'development'
Requires-Dist: pytest-httpserver==1.1.3; extra == 'development'
Requires-Dist: pytest-randomly==3.16.0; extra == 'development'
Requires-Dist: pytest==8.4.1; extra == 'development'
Requires-Dist: syrupy==4.9.1; extra == 'development'
Requires-Dist: uv>0.8.0; extra == 'development'
Provides-Extra: packaging
